Lab6/vscode/part4/part4.v
// =============================
// 1. Transparent D Latch (clk level)
// =============================
module D_latch (
    input D,
    input clk,
    output reg Q
);
    always @(*) begin
        if (clk) Q = D;   // khi clk=1 → truyền thẳng
        // khi clk=0 → giữ Q (ko gán, tức là giữ nguyên)
    end
endmodule


// =============================
// 2. D Flip-Flop posedge
// =============================
module D_ff_pos (
    input D,
    input clk,
    output reg Q
);
    always @(posedge clk) begin
        Q <= D;   // chốt tại cạnh lên
    end
endmodule


// =============================
// 3. D Flip-Flop negedge
// =============================
module D_ff_neg (
    input D,
    input clk,
    output reg Q
);
    always @(negedge clk) begin
        Q <= D;   // chốt tại cạnh xuống
    end
endmodule


// =============================
// Top module gom 3 DFF
// =============================
module part4 (
    input  D,
    input  clk,
    output Q_latch,    // latch level
    output Q_pos,      // FF posedge
    output Q_neg       // FF negedge
);

    D_latch u1 (
        .D(D),
        .clk(clk),
        .Q(Q_latch)
    );

    D_ff_pos u2 (
        .D(D),
        .clk(clk),
        .Q(Q_pos)
    );

    D_ff_neg u3 (
        .D(D),
        .clk(clk),
        .Q(Q_neg)
    );

endmodule

Lab6/vscode/part4/part4_tb.v
`timescale 1ns/1ps
`include "part4.v"
module part4_tb;
    reg clk;
    reg D;
    wire Q_latch, Q_pos, Q_neg;

    // Instantiate DUT
    part4 uut (
        .D(D),
        .clk(clk),
        .Q_latch(Q_latch),
        .Q_pos(Q_pos),
        .Q_neg(Q_neg)
    );

    // Tạo clock 10ns chu kỳ
    initial begin
        clk = 0;
        forever #5 clk = ~clk;   // 100MHz
    end

    // Sinh stimulus cho D
    initial begin
        D = 0;
        #7  D = 1;   // thay đổi không khớp biên clk
        #8  D = 0;
        #10 D = 1;
        #10 D = 0;
        #12 D = 1;
        #8  D = 0;
        #15 D = 1;
        #20 D = 0;
        #15 D = 1;
        #10 D = 0;
        #20 $finish;
    end

    // Ghi log ra console
    initial begin
        $monitor("t=%0t | clk=%b D=%b | Q_latch=%b Q_pos=%b Q_neg=%b",
                 $time, clk, D, Q_latch, Q_pos, Q_neg);
    end

    // Dump file để xem waveform
    initial begin
        $dumpfile("part4_tb.vcd");
        $dumpvars(0, part4_tb);
    end
endmodule

Lab6/vscode/part4/part4_tb.vcd
$date
	Fri Sep 26 14:24:09 2025
$end
$version
	Icarus Verilog
$end
$timescale
	1ps
$end
$scope module part4_tb $end
$var wire 1 ! Q_pos $end
$var wire 1 " Q_neg $end
$var wire 1 # Q_latch $end
$var reg 1 $ D $end
$var reg 1 % clk $end
$scope module uut $end
$var wire 1 $ D $end
$var wire 1 % clk $end
$var wire 1 ! Q_pos $end
$var wire 1 " Q_neg $end
$var wire 1 # Q_latch $end
$scope module u1 $end
$var wire 1 $ D $end
$var wire 1 % clk $end
$var reg 1 # Q $end
$upscope $end
$scope module u2 $end
$var wire 1 $ D $end
$var wire 1 % clk $end
$var reg 1 ! Q $end
$upscope $end
$scope module u3 $end
$var wire 1 $ D $end
$var wire 1 % clk $end
$var reg 1 " Q $end
$upscope $end
$upscope $end
$upscope $end
$enddefinitions $end
$comment Show the parameter values. $end
$dumpall
$end
#0
$dumpvars
0%
0$
x#
0"
x!
$end
#5000
0!
0#
1%
#7000
1#
1$
#10000
1"
0%
#15000
0#
1%
0$
#20000
0"
0%
#25000
1!
1#
1%
1$
#30000
1"
0%
#35000
0!
0#
1%
0$
#40000
0"
0%
#45000
1%
#47000
1#
1$
#50000
1"
0%
#55000
0#
1%
0$
#60000
0"
0%
#65000
1%
#70000
1"
0%
1$
#75000
1!
1#
1%
#80000
0%
#85000
1%
#90000
0"
0%
0$
#95000
0!
0#
1%
#100000
0%
#105000
1!
1#
1%
1$
#110000
1"
0%
#115000
0!
0#
1%
0$
#120000
0"
0%
