Lab6/vscode/part2/d_flip_flop.v
module D_flip_flop(
    input clk,
    input reset_n,   // reset bất đồng bộ, active low
    input D,
    output Q,
    output Qn
);

    wire n1;

    // master latch (hoạt động khi clk = 0)
    D_latch master_latch(
        .clk(~clk),
        .reset_n(reset_n),
        .D(D),
        .Q(n1),
        .Qn()
    );

    // slave latch (hoạt động khi clk = 1)
    D_latch slave_latch(
        .clk(clk),
        .reset_n(reset_n),
        .D(n1),
        .Q(Q),
        .Qn(Qn)
    );

endmodule


module D_latch(
    input clk,
    input reset_n,
    input D,
    output Q,
    output Qn
);
    wire r1, s1, Dn;

    not (Dn, D);
    and (r1, clk, Dn);
    and (s1, clk, D);

    SR_latch sr_latch(
        .S(s1),
        .R(r1),
        .reset_n(reset_n),
        .Q(Q),
        .Qn(Qn)
    );
endmodule


module SR_latch(
    input S,
    input R,
    input reset_n,
    output reg Q,
    output Qn
);
    // SR latch có reset để tránh trạng thái bất định
    always @(*) begin
        if (!reset_n) Q = 0;        // reset về 0
        else if (S & ~R) Q = 1;     // set
        else if (~S & R) Q = 0;     // reset
        // nếu S=R=0 → giữ Q
        // nếu S=R=1 → trạng thái cấm (giữ nguyên Q để tránh 'x')
    end

    assign Qn = ~Q;
endmodule


`timescale 1ns/1ps

module D_flip_flop_tb;

    reg clk;
    reg reset_n;
    reg D;
    wire Q;
    wire Qn;

    // Instantiate the D flip-flop
    D_flip_flop uut (
        .clk(clk),
        .reset_n(reset_n),
        .D(D),
        .Q(Q),
        .Qn(Qn)
    );

    // Generate clock: toggle every 5ns (period = 10ns)
    initial begin
        clk = 0;
        forever #5 clk = ~clk;
    end

    // Dump waveform
    initial begin
        $dumpfile("D_flip_flop_tb.vcd");
        $dumpvars(0, D_flip_flop_tb);
    end

    // Stimulus
    initial begin
        $display("Time\tclk\tD\tQ\tQn");
        $monitor("%4t\t%b\t%b\t%b\t%b", $time, clk, D, Q, Qn);

        // Khởi tạo
        reset_n = 0; D = 0;
        #12 reset_n = 1; // nhả reset ở thời điểm clk đang chạy

        // Test vector
        D = 0; #10;
        D = 1; #10;
        D = 0; #10;
        D = 1; #10;
        D = 0; #10;

        $finish;
    end

endmodule

Lab6/vscode/part2/D_flip_flop_tb.vcd
$date
	Fri Sep 26 13:58:34 2025
$end
$version
	Icarus Verilog
$end
$timescale
	1ps
$end
$scope module D_flip_flop_tb $end
$var wire 1 ! Qn $end
$var wire 1 " Q $end
$var reg 1 # D $end
$var reg 1 $ clk $end
$var reg 1 % reset_n $end
$scope module uut $end
$var wire 1 # D $end
$var wire 1 $ clk $end
$var wire 1 % reset_n $end
$var wire 1 & n1 $end
$var wire 1 ! Qn $end
$var wire 1 " Q $end
$scope module master_latch $end
$var wire 1 # D $end
$var wire 1 ' Dn $end
$var wire 1 ( clk $end
$var wire 1 ) r1 $end
$var wire 1 % reset_n $end
$var wire 1 * s1 $end
$var wire 1 + Qn $end
$var wire 1 & Q $end
$scope module sr_latch $end
$var wire 1 + Qn $end
$var wire 1 ) R $end
$var wire 1 * S $end
$var wire 1 % reset_n $end
$var reg 1 & Q $end
$upscope $end
$upscope $end
$scope module slave_latch $end
$var wire 1 & D $end
$var wire 1 , Dn $end
$var wire 1 $ clk $end
$var wire 1 - r1 $end
$var wire 1 % reset_n $end
$var wire 1 . s1 $end
$var wire 1 ! Qn $end
$var wire 1 " Q $end
$scope module sr_latch $end
$var wire 1 ! Qn $end
$var wire 1 - R $end
$var wire 1 . S $end
$var wire 1 % reset_n $end
$var reg 1 " Q $end
$upscope $end
$upscope $end
$upscope $end
$upscope $end
$enddefinitions $end
$comment Show the parameter values. $end
$dumpall
$end
#0
$dumpvars
0.
0-
1,
1+
0*
1)
1(
1'
0&
0%
0$
0#
0"
1!
$end
#5000
0)
0(
1-
1$
#10000
1)
1(
0-
0$
#12000
1%
#15000
0)
0(
1-
1$
#20000
1)
1(
0-
0$
#22000
0,
0+
1&
0)
0'
1*
1#
#25000
0!
0*
1"
0(
1.
1$
#30000
1*
1(
0.
0$
#32000
1,
1+
0&
1)
1'
0*
0#
#35000
1!
0)
0"
0(
1-
1$
#40000
1)
1(
0-
0$
#42000
0,
0+
1&
0)
0'
1*
1#
#45000
0!
0*
1"
0(
1.
1$
#50000
1*
1(
0.
0$
#52000
1,
1+
0&
1)
1'
0*
0#
#55000
1!
0)
0"
0(
1-
1$
#60000
1)
1(
0-
0$
