Lab7/vscode/part2.v
module part2(
    input wire clk,
    input wire rst_n,
    input wire en,

    output wire [15:0] Q
);
    reg [15:0] Q_o;

    always @(posedge clk or negedge rst_n) begin
        if (!rst_n)
            Q_o <= 16'b0;
        else if (en)
            Q_o <= Q_o + 1; // Đếm lên
    end

    assign Q = Q_o;


endmodule

`timescale 1ns/1ps

module tb_part2;

    // Inputs
    reg clk;
    reg rst_n;
    reg en;

    // Outputs
    wire [15:0] Q;

    // Instantiate the DUT
    part2 uut (
        .clk(clk),
        .rst_n(rst_n),
        .en(en),
        .Q(Q)
    );

    // Clock generation: 10ns period => 100 MHz
    initial clk = 0;
    always #5 clk = ~clk;  // Toggle every 5ns
    
    initial begin
        $dumpfile("tb_part2.vcd");
        $dumpvars(0, tb_part2);
    end

    // Test stimulus
    initial begin
        // Initialize
        rst_n = 0;
        en = 0;

        // Apply reset
        #12;
        rst_n = 1;
        en = 1;  // Enable counting

        // Let counter run for a while
        #200;

        // Disable counting
        en = 0;
        #50;

        // Re-enable counting
        en = 1;
        #100;

        // Apply reset again
        rst_n = 0;
        #10;
        rst_n = 1;

        #200; // Observe counting after reset

        $finish;
    end

    // Monitor Q
    initial begin
        $monitor("Time=%0t | rst_n=%b en=%b | Q=%h", $time, rst_n, en, Q);
    end

endmodule

Lab7/vscode/tb_part2.vcd
$date
	Tue Sep 30 06:39:57 2025
$end
$version
	Icarus Verilog
$end
$timescale
	1ps
$end
$scope module tb_part2 $end
$var wire 16 ! Q [15:0] $end
$var reg 1 " clk $end
$var reg 1 # en $end
$var reg 1 $ rst_n $end
$scope module uut $end
$var wire 16 % Q [15:0] $end
$var wire 1 " clk $end
$var wire 1 # en $end
$var wire 1 $ rst_n $end
$var reg 16 & Q_o [15:0] $end
$upscope $end
$upscope $end
$enddefinitions $end
$comment Show the parameter values. $end
$dumpall
$end
#0
$dumpvars
b0 &
b0 %
0$
0#
0"
b0 !
$end
#5000
1"
#10000
0"
#12000
1#
1$
#15000
b1 !
b1 %
b1 &
1"
#20000
0"
#25000
b10 !
b10 %
b10 &
1"
#30000
0"
#35000
b11 !
b11 %
b11 &
1"
#40000
0"
#45000
b100 !
b100 %
b100 &
1"
#50000
0"
#55000
b101 !
b101 %
b101 &
1"
#60000
0"
#65000
b110 !
b110 %
b110 &
1"
#70000
0"
#75000
b111 !
b111 %
b111 &
1"
#80000
0"
#85000
b1000 !
b1000 %
b1000 &
1"
#90000
0"
#95000
b1001 !
b1001 %
b1001 &
1"
#100000
0"
#105000
b1010 !
b1010 %
b1010 &
1"
#110000
0"
#115000
b1011 !
b1011 %
b1011 &
1"
#120000
0"
#125000
b1100 !
b1100 %
b1100 &
1"
#130000
0"
#135000
b1101 !
b1101 %
b1101 &
1"
#140000
0"
#145000
b1110 !
b1110 %
b1110 &
1"
#150000
0"
#155000
b1111 !
b1111 %
b1111 &
1"
#160000
0"
#165000
b10000 !
b10000 %
b10000 &
1"
#170000
0"
#175000
b10001 !
b10001 %
b10001 &
1"
#180000
0"
#185000
b10010 !
b10010 %
b10010 &
1"
#190000
0"
#195000
b10011 !
b10011 %
b10011 &
1"
#200000
0"
#205000
b10100 !
b10100 %
b10100 &
1"
#210000
0"
#212000
0#
#215000
1"
#220000
0"
#225000
1"
#230000
0"
#235000
1"
#240000
0"
#245000
1"
#250000
0"
#255000
1"
#260000
0"
#262000
1#
#265000
b10101 !
b10101 %
b10101 &
1"
#270000
0"
#275000
b10110 !
b10110 %
b10110 &
1"
#280000
0"
#285000
b10111 !
b10111 %
b10111 &
1"
#290000
0"
#295000
b11000 !
b11000 %
b11000 &
1"
#300000
0"
#305000
b11001 !
b11001 %
b11001 &
1"
#310000
0"
#315000
b11010 !
b11010 %
b11010 &
1"
#320000
0"
#325000
b11011 !
b11011 %
b11011 &
1"
#330000
0"
#335000
b11100 !
b11100 %
b11100 &
1"
#340000
0"
#345000
b11101 !
b11101 %
b11101 &
1"
#350000
0"
#355000
b11110 !
b11110 %
b11110 &
1"
#360000
0"
#362000
b0 !
b0 %
b0 &
0$
#365000
1"
#370000
0"
#372000
1$
#375000
b1 !
b1 %
b1 &
1"
#380000
0"
#385000
b10 !
b10 %
b10 &
1"
#390000
0"
#395000
b11 !
b11 %
b11 &
1"
#400000
0"
#405000
b100 !
b100 %
b100 &
1"
#410000
0"
#415000
b101 !
b101 %
b101 &
1"
#420000
0"
#425000
b110 !
b110 %
b110 &
1"
#430000
0"
#435000
b111 !
b111 %
b111 &
1"
#440000
0"
#445000
b1000 !
b1000 %
b1000 &
1"
#450000
0"
#455000
b1001 !
b1001 %
b1001 &
1"
#460000
0"
#465000
b1010 !
b1010 %
b1010 &
1"
#470000
0"
#475000
b1011 !
b1011 %
b1011 &
1"
#480000
0"
#485000
b1100 !
b1100 %
b1100 &
1"
#490000
0"
#495000
b1101 !
b1101 %
b1101 &
1"
#500000
0"
#505000
b1110 !
b1110 %
b1110 &
1"
#510000
0"
#515000
b1111 !
b1111 %
b1111 &
1"
#520000
0"
#525000
b10000 !
b10000 %
b10000 &
1"
#530000
0"
#535000
b10001 !
b10001 %
b10001 &
1"
#540000
0"
#545000
b10010 !
b10010 %
b10010 &
1"
#550000
0"
#555000
b10011 !
b10011 %
b10011 &
1"
#560000
0"
#565000
b10100 !
b10100 %
b10100 &
1"
