Lab6/vscode/part1/part1.v
module part1 (
    input clk, R, S,
    output Q
);

    wire R_g, S_g, Qa, Qb;

    assign R_g = R & clk;
    assign S_g = S & clk;
    assign Qa  = ~(R_g | Qb);
    assign Qb  = ~(S_g | Qa);

    assign Q = Qa;

endmodule

Lab6/vscode/part1/tb_part1.v
`timescale 1ns/1ps
`include "part1.v"
module tb_part1;
    reg clk, R, S;
    wire Q;

    // DUT
    part1 uut (
        .clk(clk),
        .R(R),
        .S(S),
        .Q(Q)
    );

    // Clock 10ns period
    initial begin
        clk = 0;
        forever #5 clk = ~clk;
    end

    // Test stimulus
    initial begin
        $dumpfile("tb_part1.vcd");  // dùng cho GTKWave
        $dumpvars(0, tb_part1);

        // Init
        R = 0; S = 0;

        // giữ cả R và S = 0
        #20;

        // Set = 1
        S = 1; R = 0;
        #20;

        // Reset = 1
        S = 0; R = 1;
        #20;

        // R = S = 0 (hold state)
        R = 0; S = 0;
        #20;

        // Trường hợp không xác định R=1, S=1
        R = 1; S = 1;
        #20;

        // Quay về hold
        R = 0; S = 0;
        #20;

        $finish;
    end
endmodule

Lab6/vscode/part1/tb_part1.vcd
$date
	Fri Sep 26 13:49:49 2025
$end
$version
	Icarus Verilog
$end
$timescale
	1ps
$end
$scope module tb_part1 $end
$var wire 1 ! Q $end
$var reg 1 " R $end
$var reg 1 # S $end
$var reg 1 $ clk $end
$scope module uut $end
$var wire 1 ! Q $end
$var wire 1 % Qa $end
$var wire 1 & Qb $end
$var wire 1 " R $end
$var wire 1 ' R_g $end
$var wire 1 # S $end
$var wire 1 ( S_g $end
$var wire 1 $ clk $end
$upscope $end
$upscope $end
$enddefinitions $end
$comment Show the parameter values. $end
$dumpall
$end
#0
$dumpvars
0(
0'
x&
x%
0$
0#
0"
x!
$end
#5000
1$
#10000
0$
#15000
1$
#20000
0$
1#
#25000
1!
1%
0&
1(
1$
#30000
0(
0$
#35000
1(
1$
#40000
0(
0$
1"
0#
#45000
1&
0!
0%
1'
1$
#50000
0'
0$
#55000
1'
1$
#60000
0'
0$
0"
#65000
1$
#70000
0$
#75000
1$
#80000
0$
1#
1"
#85000
0&
1'
1(
1$
