Lab8/vscode/part1.v
module part1#(
    parameter n = 8,
    parameter k = 10
)(
    input clk,
    input rst,
    output reg [n-1:0] count
);

    always @(posedge clk or negedge rst) begin
        if(!rst) begin
            count <= 0;
        end else if(count == k-1) begin
            count <= 0;
        end else begin
            count <= count + 1;
        end
        
    end

endmodule

// module top (
//     input  wire [1:0] KEY,      // KEY0 = reset_n, KEY1 = clock
//     output wire [7:0] LEDR      // hiển thị Q trên LED
// );

//     wire clock = KEY[1];
//     wire reset_n = KEY[0];

//     counter_modk #(8, 10) u0 (   // 8-bit, modulo-10
//         .clock(clock),
//         .reset_n(reset_n),
//         .Q(LEDR)
//     );

// endmodule

`timescale 1ns/1ps

module tb_part1;

    // Tham số test
    parameter N = 8;
    parameter K = 10;

    // Tín hiệu kết nối
    reg  clock;
    reg  reset_n;
    wire [N-1:0] Q;

    // Instantiate DUT (Device Under Test)
    part1 #(N, K) uut (
        .clk(clock),
        .rst(reset_n),
        .count(Q)
    );

    // Tạo clock 10ns chu kỳ (100 MHz)
    initial begin
        clock = 0;
        forever #5 clock = ~clock; // toggle mỗi 5ns
    end

    initial begin
        $dumpfile("tb_part1.vcd");
        $dumpvars(0, tb_part1);    
    end

    // Stimulus
    initial begin
        $display("=== Testbench for modulo-%0d counter ===", K);

        // Reset ban đầu
        reset_n = 0;
        #12;                // giữ reset vài chu kỳ
        reset_n = 1;

        // Để counter chạy đủ nhiều để thấy nó quay về 0
        #200;

        // Kích hoạt reset giữa chừng
        reset_n = 0;
        #10;
        reset_n = 1;

        #100;

        $finish;  // kết thúc mô phỏng
    end

    // Monitor giá trị counter
    initial begin
        $monitor("Time=%0t | reset_n=%b | Q=%0d", $time, reset_n, Q);
    end

endmodule

Lab8/vscode/tb_part1.vcd
$date
	Tue Sep 30 14:51:46 2025
$end
$version
	Icarus Verilog
$end
$timescale
	1ps
$end
$scope module tb_part1 $end
$var wire 8 ! Q [7:0] $end
$var parameter 32 " K $end
$var parameter 32 # N $end
$var reg 1 $ clock $end
$var reg 1 % reset_n $end
$scope module uut $end
$var wire 1 $ clk $end
$var wire 1 % rst $end
$var parameter 32 & k $end
$var parameter 32 ' n $end
$var reg 8 ( count [7:0] $end
$upscope $end
$upscope $end
$enddefinitions $end
$comment Show the parameter values. $end
$dumpall
b1000 '
b1010 &
b1000 #
b1010 "
$end
#0
$dumpvars
b0 (
0%
0$
b0 !
$end
#5000
1$
#10000
0$
#12000
1%
#15000
b1 !
b1 (
1$
#20000
0$
#25000
b10 !
b10 (
1$
#30000
0$
#35000
b11 !
b11 (
1$
#40000
0$
#45000
b100 !
b100 (
1$
#50000
0$
#55000
b101 !
b101 (
1$
#60000
0$
#65000
b110 !
b110 (
1$
#70000
0$
#75000
b111 !
b111 (
1$
#80000
0$
#85000
b1000 !
b1000 (
1$
#90000
0$
#95000
b1001 !
b1001 (
1$
#100000
0$
#105000
b0 !
b0 (
1$
#110000
0$
#115000
b1 !
b1 (
1$
#120000
0$
#125000
b10 !
b10 (
1$
#130000
0$
#135000
b11 !
b11 (
1$
#140000
0$
#145000
b100 !
b100 (
1$
#150000
0$
#155000
b101 !
b101 (
1$
#160000
0$
#165000
b110 !
b110 (
1$
#170000
0$
#175000
b111 !
b111 (
1$
#180000
0$
#185000
b1000 !
b1000 (
1$
#190000
0$
#195000
b1001 !
b1001 (
1$
#200000
0$
#205000
b0 !
b0 (
1$
#210000
0$
#212000
0%
#215000
1$
#220000
0$
#222000
1%
#225000
b1 !
b1 (
1$
#230000
0$
#235000
b10 !
b10 (
1$
#240000
0$
#245000
b11 !
b11 (
1$
#250000
0$
#255000
b100 !
b100 (
1$
#260000
0$
#265000
b101 !
b101 (
1$
#270000
0$
#275000
b110 !
b110 (
1$
#280000
0$
#285000
b111 !
b111 (
1$
#290000
0$
#295000
b1000 !
b1000 (
1$
#300000
0$
#305000
b1001 !
b1001 (
1$
#310000
0$
#315000
b0 !
b0 (
1$
